{"start":1701851939615,"end":1701851948151,"delta":8536,"records":[{"index":0,"name":"createDiplomaCredential","start":1701851939615,"end":1701851939615,"delta":0,"tag":"university","className":"SolidVCActor"},{"index":1,"name":"signDiplomaCredential","start":1701851939615,"end":1701851940237,"delta":622,"tag":"university","className":"SolidVCActor"},{"index":2,"name":"createIdentityCredential","start":1701851940237,"end":1701851940237,"delta":0,"tag":"government","className":"SolidVCActor"},{"index":3,"name":"signIdentityCredential","start":1701851940237,"end":1701851941151,"delta":914,"tag":"government","className":"SolidVCActor"},{"index":4,"name":"deriveDiplomaCredential","start":1701851941151,"end":1701851944159,"delta":3008,"tag":"alice","className":"CompoundCredentialActor<SolidVCActor,SolidVCActor>"},{"index":5,"name":"createPresentation01","start":1701851944159,"end":1701851944159,"delta":0,"tag":"alice","className":"CompoundCredentialActor<SolidVCActor,SolidVCActor>"},{"index":6,"name":"signPresentation01","start":1701851944159,"end":1701851944344,"delta":185,"tag":"alice","className":"CompoundCredentialActor<SolidVCActor,SolidVCActor>"},{"index":7,"name":"verifyPresentation01","start":1701851944344,"end":1701851944626,"delta":282,"tag":"recruiter","className":"SolidVCActor"},{"index":8,"name":"deriveIdentityCredential","start":1701851944626,"end":1701851947718,"delta":3092,"tag":"alice","className":"CompoundCredentialActor<SolidVCActor,SolidVCActor>"},{"index":9,"name":"createPresentation02","start":1701851947718,"end":1701851947718,"delta":0,"tag":"alice","className":"CompoundCredentialActor<SolidVCActor,SolidVCActor>"},{"index":10,"name":"signPresentation02","start":1701851947718,"end":1701851947896,"delta":178,"tag":"alice","className":"CompoundCredentialActor<SolidVCActor,SolidVCActor>"},{"index":11,"name":"verifyPresentation02","start":1701851947896,"end":1701851948151,"delta":255,"tag":"recruiter","className":"SolidVCActor"}],"documentLoaderCacheOptions":{"DID":{"cacheResolvedDIDDocs":false},"HTTP":{"cacheWebResourcesResolvedFromLocalHostInstances":false,"cacheWebResourcesResolvedFromTheWeb":false}},"hostReport":{"platform":"darwin","machine":"arm64","arch":"arm64","cpus":[{"model":"Apple M1 Max","speed":24},{"model":"Apple M1 Max","speed":24},{"model":"Apple M1 Max","speed":24},{"model":"Apple M1 Max","speed":24},{"model":"Apple M1 Max","speed":24},{"model":"Apple M1 Max","speed":24},{"model":"Apple M1 Max","speed":24},{"model":"Apple M1 Max","speed":24},{"model":"Apple M1 Max","speed":24},{"model":"Apple M1 Max","speed":24}],"type":"Darwin","totalmem":34359738368,"freemem":262275072,"uptime":149858}}