{"start":1701852228904,"end":1701852236788,"delta":7884,"records":[{"index":0,"name":"createDiplomaCredential","start":1701852228904,"end":1701852228904,"delta":0,"tag":"university","className":"SolidVCActor"},{"index":1,"name":"signDiplomaCredential","start":1701852228904,"end":1701852229517,"delta":613,"tag":"university","className":"SolidVCActor"},{"index":2,"name":"createIdentityCredential","start":1701852229517,"end":1701852229517,"delta":0,"tag":"government","className":"SolidVCActor"},{"index":3,"name":"signIdentityCredential","start":1701852229517,"end":1701852230178,"delta":661,"tag":"government","className":"SolidVCActor"},{"index":4,"name":"deriveDiplomaCredential","start":1701852230178,"end":1701852233065,"delta":2887,"tag":"alice","className":"CompoundCredentialActor<SolidVCActor,SolidVCActor>"},{"index":5,"name":"createPresentation01","start":1701852233065,"end":1701852233065,"delta":0,"tag":"alice","className":"CompoundCredentialActor<SolidVCActor,SolidVCActor>"},{"index":6,"name":"signPresentation01","start":1701852233065,"end":1701852233248,"delta":183,"tag":"alice","className":"CompoundCredentialActor<SolidVCActor,SolidVCActor>"},{"index":7,"name":"verifyPresentation01","start":1701852233248,"end":1701852233513,"delta":265,"tag":"recruiter","className":"SolidVCActor"},{"index":8,"name":"deriveIdentityCredential","start":1701852233513,"end":1701852236356,"delta":2843,"tag":"alice","className":"CompoundCredentialActor<SolidVCActor,SolidVCActor>"},{"index":9,"name":"createPresentation02","start":1701852236356,"end":1701852236356,"delta":0,"tag":"alice","className":"CompoundCredentialActor<SolidVCActor,SolidVCActor>"},{"index":10,"name":"signPresentation02","start":1701852236356,"end":1701852236539,"delta":183,"tag":"alice","className":"CompoundCredentialActor<SolidVCActor,SolidVCActor>"},{"index":11,"name":"verifyPresentation02","start":1701852236539,"end":1701852236788,"delta":249,"tag":"recruiter","className":"SolidVCActor"}],"documentLoaderCacheOptions":{"DID":{"cacheResolvedDIDDocs":false},"HTTP":{"cacheWebResourcesResolvedFromLocalHostInstances":false,"cacheWebResourcesResolvedFromTheWeb":false}},"hostReport":{"platform":"darwin","machine":"arm64","arch":"arm64","cpus":[{"model":"Apple M1 Max","speed":24},{"model":"Apple M1 Max","speed":24},{"model":"Apple M1 Max","speed":24},{"model":"Apple M1 Max","speed":24},{"model":"Apple M1 Max","speed":24},{"model":"Apple M1 Max","speed":24},{"model":"Apple M1 Max","speed":24},{"model":"Apple M1 Max","speed":24},{"model":"Apple M1 Max","speed":24},{"model":"Apple M1 Max","speed":24}],"type":"Darwin","totalmem":34359738368,"freemem":969441280,"uptime":150147}}