{"start":1701855244009,"end":1701855252558,"delta":8549,"records":[{"index":0,"name":"createDiplomaCredential","start":1701855244009,"end":1701855244009,"delta":0,"tag":"university","className":"SolidVCActor"},{"index":1,"name":"signDiplomaCredential","start":1701855244009,"end":1701855244600,"delta":591,"tag":"university","className":"SolidVCActor"},{"index":2,"name":"createIdentityCredential","start":1701855244600,"end":1701855244600,"delta":0,"tag":"government","className":"SolidVCActor"},{"index":3,"name":"signIdentityCredential","start":1701855244600,"end":1701855245212,"delta":612,"tag":"government","className":"SolidVCActor"},{"index":4,"name":"deriveDiplomaCredential","start":1701855245212,"end":1701855248028,"delta":2816,"tag":"alice","className":"CompoundCredentialActor<SolidVCActor,DidVCActor>"},{"index":5,"name":"createPresentation01","start":1701855248028,"end":1701855248028,"delta":0,"tag":"alice","className":"CompoundCredentialActor<SolidVCActor,DidVCActor>"},{"index":6,"name":"signPresentation01","start":1701855248028,"end":1701855248261,"delta":233,"tag":"alice","className":"CompoundCredentialActor<SolidVCActor,DidVCActor>"},{"index":7,"name":"verifyPresentation01","start":1701855248261,"end":1701855249018,"delta":757,"tag":"recruiter","className":"SolidVCActor"},{"index":8,"name":"deriveIdentityCredential","start":1701855249018,"end":1701855252076,"delta":3058,"tag":"alice","className":"CompoundCredentialActor<SolidVCActor,DidVCActor>"},{"index":9,"name":"createPresentation02","start":1701855252076,"end":1701855252076,"delta":0,"tag":"alice","className":"CompoundCredentialActor<SolidVCActor,DidVCActor>"},{"index":10,"name":"signPresentation02","start":1701855252076,"end":1701855252256,"delta":180,"tag":"alice","className":"CompoundCredentialActor<SolidVCActor,DidVCActor>"},{"index":11,"name":"verifyPresentation02","start":1701855252256,"end":1701855252558,"delta":302,"tag":"recruiter","className":"SolidVCActor"}],"documentLoaderCacheOptions":{"DID":{"cacheResolvedDIDDocs":false},"HTTP":{"cacheWebResourcesResolvedFromLocalHostInstances":false,"cacheWebResourcesResolvedFromTheWeb":false}},"hostReport":{"platform":"darwin","machine":"arm64","arch":"arm64","cpus":[{"model":"Apple M1 Max","speed":24},{"model":"Apple M1 Max","speed":24},{"model":"Apple M1 Max","speed":24},{"model":"Apple M1 Max","speed":24},{"model":"Apple M1 Max","speed":24},{"model":"Apple M1 Max","speed":24},{"model":"Apple M1 Max","speed":24},{"model":"Apple M1 Max","speed":24},{"model":"Apple M1 Max","speed":24},{"model":"Apple M1 Max","speed":24}],"type":"Darwin","totalmem":34359738368,"freemem":1072726016,"uptime":153163}}